sql_insert_writer/__init__.py
sql_insert_writer/cli.py
sql_insert_writer/sql_insert_writer.py
sql_insert_writer-0.1.0.dist-info/DESCRIPTION.rst
sql_insert_writer-0.1.0.dist-info/METADATA
sql_insert_writer-0.1.0.dist-info/RECORD
sql_insert_writer-0.1.0.dist-info/WHEEL
sql_insert_writer-0.1.0.dist-info/entry_points.txt
sql_insert_writer-0.1.0.dist-info/metadata.json
sql_insert_writer-0.1.0.dist-info/top_level.txt
