Metadata-Version: 2.0
Name: sql-insert-writer
Version: 0.1.0
Summary: Helps make long SQL INSERT statements readable
Home-page: https://github.com/18F/sql_insert_writer
Author: 18F
Author-email: catherine.devlin@gsa.gov
License: CC0 license
Keywords: sql_insert_writer
Platform: UNKNOWN
Classifier: Development Status :: 2 - Pre-Alpha
Classifier: Intended Audience :: Developers
Classifier: License :: CC0 1.0 Universal (CC0 1.0) Public Domain Dedication
Classifier: Natural Language :: English
Classifier: Programming Language :: Python :: 3
Classifier: Programming Language :: Python :: 3.3
Classifier: Programming Language :: Python :: 3.4
Classifier: Programming Language :: Python :: 3.5
Classifier: Programming Language :: Python :: 3.6
Classifier: Programming Language :: SQL
Classifier: Topic :: Database
Classifier: Topic :: Software Development :: Code Generators
Requires-Dist: Click (>=6.7)
Requires-Dist: records (==0.5.2)
Requires-Dist: attrdict (==2.0.0)
